{
	"Testing frameworks": {
		"mocha": 306,
		"jest": 121,
		"tap": 85,
		"ava": 59,
		"tsd": 44,
		"tape": 40,
		"karma": 30,
		"flow": 11,
		"nodeunit": 11,
		"vows": 10,
		"lab": 8,
		"jasmine": 7,
		"zuul": 1,
		"zap": 1,
		"cypress": 0,
		"ocular-test": 0,
		"expresso": 0,
		"testem": 0
	},
	"Code analysis tool": {
		"eslint": 129,
		"xo": 68,
		"standard": 37,
		"tslint": 21,
		"dtslint": 15,
		"jshint": 13,
		"c8": 8,
		"semistandard": 4,
		"coffeelint": 0
	},
	"Task runner": {
		"grunt": 35,
		"gulp": 19,
		"lerna": 12,
		"ember": 4,
		"wsrun": 1,
		"nwb": 0,
		"aegir": 0
	},
	"Build tool": {
		"make": 43
	},
	"Browser": {
		"phantomjs": 3
	},
	"other": 102,
	"undefined": 75
}